notesviewer/__init__.py
notesviewer/_version
notesviewer/commands.py
notesviewer/config.py
notesviewer/error.py
notesviewer/file.py
notesviewer/interactive.py
notesviewer/note.py
notesviewer/nv.py
notesviewer/utils.py
notesviewer/vardata.py
notesviewer-0.9.5.2.10.data/data/share/docs/notesviewer/README.md
notesviewer-0.9.5.2.10.data/data/share/docs/notesviewer/bash_prompt.txt
notesviewer-0.9.5.2.10.dist-info/LICENSE
notesviewer-0.9.5.2.10.dist-info/METADATA
notesviewer-0.9.5.2.10.dist-info/WHEEL
notesviewer-0.9.5.2.10.dist-info/entry_points.txt
notesviewer-0.9.5.2.10.dist-info/top_level.txt
notesviewer-0.9.5.2.10.dist-info/RECORD
