Metadata-Version: 2.1
Name: notesviewer
Version: 0.9.5.2.10
Summary: notesviewer
Home-page: https://gitlab.com/Alekgr/notesviewer.git
Author: alekgr
Author-email: alek.grigorian@gmail.com
License: GPL
Platform: UNKNOWN
Classifier: Development Status :: 3 - Alpha
Classifier: Intended Audience :: Developers
Classifier: License :: OSI Approved :: GNU General Public License v2 (GPLv2)
Classifier: Programming Language :: Python :: 3.4
Classifier: Programming Language :: Python :: 3.5
Classifier: Programming Language :: Python :: 3.6
Classifier: Programming Language :: Python :: 3.7
Classifier: Topic :: System :: Operating System Kernels :: Linux
Requires-Dist: termcolor
Requires-Dist: configparser
